{"height":13,"layers":[{"data":[1,1,1,1,1,1,1,1,1,1,1,1,1,1,1,1,1,1,3,3,3,1,1,1,3,3,3,1,1,1,3,3,3,1,1,3,3,3,1,1,1,3,3,3,1,1,1,3,3,3,1,1,3,3,3,1,1,1,3,3,3,1,1,1,3,3,3,1,1,3,3,3,3,3,3,3,3,3,3,3,3,3,3,3,1,1,3,3,3,3,3,3,3,3,3,3,3,3,3,3,3,1,1,3,3,3,3,3,3,3,3,3,3,3,3,3,3,3,1,1,3,3,3,3,3,3,3,3,3,3,3,3,3,3,3,1,1,3,3,3,3,3,3,3,3,3,3,3,3,3,3,3,1,1,3,3,3,3,3,3,3,3,3,3,3,3,3,3,3,1,1,3,3,3,3,3,3,3,3,3,3,3,3,3,3,3,1,1,3,3,3,3,3,3,3,3,3,3,3,3,3,3,3,1,1,1,1,1,1,1,1,1,1,1,1,1,1,1,1,1,1],"height":13,"name":"Tile Layer 1","opacity":1,"type":"tilelayer","visible":true,"width":17,"x":0,"y":0},{"draworder":"topdown","name":"Object Layer 1","objects":[{"gid":67,"height":40,"id":244,"name":"","properties":{"objectType":"Pillar"},"propertytypes":{"objectType":"string"},"rotation":0,"type":"","visible":true,"width":20,"x":40,"y":120},{"gid":67,"height":40,"id":260,"name":"","properties":{"objectType":"Pillar"},"propertytypes":{"objectType":"string"},"rotation":0,"type":"","visible":true,"width":20,"x":160,"y":120},{"gid":67,"height":40,"id":262,"name":"","properties":{"objectType":"Pillar"},"propertytypes":{"objectType":"string"},"rotation":0,"type":"","visible":true,"width":20,"x":280,"y":120},{"gid":67,"height":40,"id":265,"name":"","properties":{"objectType":"Pillar"},"propertytypes":{"objectType":"string"},"rotation":0,"type":"","visible":true,"width":20,"x":40,"y":220},{"gid":67,"height":40,"id":266,"name":"","properties":{"objectType":"Pillar"},"propertytypes":{"objectType":"string"},"rotation":0,"type":"","visible":true,"width":20,"x":160,"y":220},{"gid":67,"height":40,"id":267,"name":"","properties":{"objectType":"Pillar"},"propertytypes":{"objectType":"string"},"rotation":0,"type":"","visible":true,"width":20,"x":280,"y":220},{"height":120,"id":268,"name":"","properties":{"tag":"&Center"},"propertytypes":{"tag":"string"},"rotation":0,"type":"","visible":true,"width":260,"x":40,"y":100},{"height":20,"id":269,"name":"","properties":{"tag":"&BackWall"},"propertytypes":{"tag":"string"},"rotation":0,"type":"","visible":true,"width":60,"x":20,"y":20},{"height":20,"id":270,"name":"","properties":{"tag":"&BackWall"},"propertytypes":{"tag":"string"},"rotation":0,"type":"","visible":true,"width":60,"x":140,"y":20},{"height":20,"id":271,"name":"","properties":{"tag":"&BackWall"},"propertytypes":{"tag":"string"},"rotation":0,"type":"","visible":true,"width":60,"x":260,"y":20},{"height":20,"id":272,"name":"","properties":{"tag":"&BackWall"},"propertytypes":{"tag":"string"},"rotation":0,"type":"","visible":true,"width":60,"x":140,"y":220}],"opacity":1,"type":"objectgroup","visible":true,"x":0,"y":0},{"data":[65,65,0,65,65,65,65,65,0,65,65,65,65,65,0,65,65,65,0,0,0,65,65,65,0,0,0,65,65,65,0,0,0,65,65,0,0,0,65,65,65,0,0,0,65,65,65,0,0,0,65,65,0,0,0,65,65,65,0,0,0,65,65,65,0,0,0,65,0,0,0,0,0,0,0,0,0,0,0,0,0,0,0,0,0,0,0,70,70,70,70,70,70,70,70,70,70,70,70,70,0,0,0,0,70,70,70,70,70,70,70,70,70,70,70,70,70,0,0,0,0,70,70,70,70,70,70,70,70,70,70,70,70,70,0,0,0,0,70,70,70,70,70,70,70,70,70,70,70,70,70,0,0,0,0,70,70,70,70,70,70,70,70,70,70,70,70,70,0,0,0,0,70,70,70,70,70,70,70,70,70,70,70,70,70,0,0,65,0,0,0,0,0,0,0,0,0,0,0,0,0,0,0,65,65,65,0,0,0,0,0,0,0,0,0,0,0,0,0,65,65],"height":13,"name":"Tile Layer 2","opacity":1,"type":"tilelayer","visible":true,"width":17,"x":0,"y":0}],"nextobjectid":273,"orientation":"orthogonal","renderorder":"right-down","tiledversion":"1.0.3","tileheight":20,"tilesets":[{"firstgid":1,"source":"../../../MapTileset.tsx"},{"firstgid":5249,"source":"../../../Tileset.tsx"}],"tilewidth":20,"type":"map","version":1,"width":17,"properties":{"allowRotate":false},"propertytypes":{"allowRotate":"bool"}}